shno_lib/__init__.py
shno_lib/data_io/__init__.py
shno_lib/data_io/es_query.py
shno_lib/data_io/file_io.py
shno_lib/data_io/import_data.py
shno_lib/data_proc/__init__.py
shno_lib/data_proc/data_filter.py
shno_lib/data_proc/data_trans.py
shno_lib/data_proc/dir_exec.py
shno_lib/rotate_output/__init__.py
shno_lib/rotate_output/daily_rotate_output.py
shno_lib/rotate_output/interval_rotate_output.py
shno_lib/rotate_output/rotate_output.py
shno_lib-0.1.16.dist-info/METADATA
shno_lib-0.1.16.dist-info/WHEEL
shno_lib-0.1.16.dist-info/top_level.txt
shno_lib-0.1.16.dist-info/RECORD
