Metadata-Version: 2.1
Name: shno-lib
Version: 0.1.16
Summary: shnovaj30101's util library
Home-page: https://git.taiw.in/shnovaj30101/shno_lib
Author: shnovaj30101
Author-email: shnovaj30101@gmail.com
License: UNKNOWN
Platform: UNKNOWN
